accel_hydra/__init__.py
accel_hydra/train_entry.py
accel_hydra/train_launcher.py
accel_hydra/data_module/collate_function.py
accel_hydra/data_module/sampler.py
accel_hydra/losses/__init__.py
accel_hydra/losses/base.py
accel_hydra/models/__init__.py
accel_hydra/models/common.py
accel_hydra/trainer/__init__.py
accel_hydra/trainer/base.py
accel_hydra/utils/__init__.py
accel_hydra/utils/accelerate.py
accel_hydra/utils/config.py
accel_hydra/utils/data.py
accel_hydra/utils/general.py
accel_hydra/utils/logging.py
accel_hydra/utils/lr_scheduler.py
accel_hydra/utils/torch.py
accel_hydra-0.0.4.dist-info/METADATA
accel_hydra-0.0.4.dist-info/WHEEL
accel_hydra-0.0.4.dist-info/licenses/LICENSE
accel_hydra-0.0.4.dist-info/RECORD
