Metadata-Version: 2.4
Name: accel_hydra
Version: 0.0.4
Summary: AccelHydra is a lightweight, modular, configurable training framework built on Accelerate and Hydra
Project-URL: Homepage, https://github.com/wsntxxn/AccelHydra
Project-URL: Bug Tracker, https://github.com/wsntxxn/AccelHydra/issues
License-File: LICENSE
Classifier: License :: Other/Proprietary License
Classifier: Operating System :: OS Independent
Classifier: Programming Language :: Python :: 3
Requires-Python: >=3.10
Requires-Dist: accelerate>=1.0.0
Requires-Dist: hydra-core>=1.3.0
Requires-Dist: omegaconf>=2.1.0
Requires-Dist: torch>=1.13.0
Requires-Dist: tqdm>=4.0.0
